<annotation>
	<folder>Etiquetado</folder>
	<filename>179.PNG</filename>
	<path>C:\Users\diemayba\Desktop\resolucion\Etiquetado\179.PNG</path>
	<source>
		<database>Unknown</database>
	</source>
	<size>
		<width>640</width>
		<height>640</height>
		<depth>3</depth>
	</size>
	<segmented>0</segmented>
	<object>
		<name>D20</name>
		<pose>Unspecified</pose>
		<truncated>0</truncated>
		<difficult>0</difficult>
		<bndbox>
			<xmin>275</xmin>
			<ymin>549</ymin>
			<xmax>405</xmax>
			<ymax>619</ymax>
		</bndbox>
	</object>
	<object>
		<name>D00</name>
		<pose>Unspecified</pose>
		<truncated>0</truncated>
		<difficult>0</difficult>
		<bndbox>
			<xmin>277</xmin>
			<ymin>478</ymin>
			<xmax>288</xmax>
			<ymax>546</ymax>
		</bndbox>
	</object>
</annotation>
