<annotation>
	<folder>Etiquetado</folder>
	<filename>296.PNG</filename>
	<path>C:\Users\diemayba\Desktop\resolucion\Etiquetado\296.PNG</path>
	<source>
		<database>Unknown</database>
	</source>
	<size>
		<width>640</width>
		<height>640</height>
		<depth>3</depth>
	</size>
	<segmented>0</segmented>
	<object>
		<name>D10</name>
		<pose>Unspecified</pose>
		<truncated>0</truncated>
		<difficult>0</difficult>
		<bndbox>
			<xmin>89</xmin>
			<ymin>597</ymin>
			<xmax>136</xmax>
			<ymax>617</ymax>
		</bndbox>
	</object>
	<object>
		<name>D20</name>
		<pose>Unspecified</pose>
		<truncated>0</truncated>
		<difficult>0</difficult>
		<bndbox>
			<xmin>150</xmin>
			<ymin>483</ymin>
			<xmax>353</xmax>
			<ymax>622</ymax>
		</bndbox>
	</object>
</annotation>
